pyaml_processor/__init__.py
pyaml_processor/__main__.py
pyaml_processor/capture.py
pyaml_processor-0.4.0.dist-info/entry_points.txt
pyaml_processor-0.4.0.dist-info/WHEEL
pyaml_processor-0.4.0.dist-info/METADATA
pyaml_processor-0.4.0.dist-info/RECORD
