Metadata-Version: 2.1
Name: pyaml-processor
Version: 0.4.0
Summary: Library for embedding Python code in YAML.
Home-page: https://github.com/gwww/pyaml
License: MIT
Author: Glenn Waters
Author-email: gwwaters+pyaml@gmail.com
Requires-Python: >=3.6,<4.0
Classifier: Development Status :: 4 - Beta
Classifier: Intended Audience :: Developers
Classifier: License :: OSI Approved :: MIT License
Classifier: Programming Language :: Python :: 3
Classifier: Programming Language :: Python :: 3.6
Classifier: Programming Language :: Python :: 3.7
Classifier: Programming Language :: Python :: 3.8
Requires-Dist: PyYAML (>=5.3,<6.0)
